compress_mail/__init__.py
compress_mail/_version.py
compress_mail/compress_mail.py
compress_mail/lockmaildir.py
compress_mail-1.0.9.dist-info/METADATA
compress_mail-1.0.9.dist-info/WHEEL
compress_mail-1.0.9.dist-info/entry_points.txt
compress_mail-1.0.9.dist-info/RECORD
