Metadata-Version: 2.4
Name: compress-mail
Version: 1.0.9
Summary: A utility to compress email messages for use with dovecot.
Project-URL: Documentation, https://github.com/lingfish/compress-mail#readme
Project-URL: Issues, https://github.com/lingfish/compress-mail/issues
Project-URL: Source, https://github.com/lingfish/compress-mail
Author-email: lingfish <jason@lucid.net.au>
License-Expression: MIT
Classifier: Development Status :: 4 - Beta
Classifier: Programming Language :: Python
Classifier: Programming Language :: Python :: 3.8
Classifier: Programming Language :: Python :: 3.9
Classifier: Programming Language :: Python :: 3.10
Classifier: Programming Language :: Python :: 3.11
Classifier: Programming Language :: Python :: 3.12
Classifier: Programming Language :: Python :: Implementation :: CPython
Classifier: Programming Language :: Python :: Implementation :: PyPy
Requires-Python: >=3.8
Requires-Dist: click
Requires-Dist: rich
